installdist.py
installdist-0.2.1.dist-info/METADATA
installdist-0.2.1.dist-info/entry_points.txt
installdist-0.2.1.dist-info/top_level.txt
installdist-0.2.1.dist-info/pbr.json
installdist-0.2.1.dist-info/WHEEL
installdist-0.2.1.dist-info/metadata.json
installdist-0.2.1.dist-info/DESCRIPTION.rst
installdist-0.2.1.dist-info/RECORD
